jinja_rdf/__init__.py
jinja_rdf/graph_handling.py
jinja_rdf/rdf_property.py
jinja_rdf/rdf_resource.py
jinja_rdf/sparql_query.py
jinja_rdf-0.1.6.dist-info/METADATA
jinja_rdf-0.1.6.dist-info/WHEEL
jinja_rdf-0.1.6.dist-info/licenses/LICENSE.txt
jinja_rdf-0.1.6.dist-info/RECORD
