Metadata-Version: 2.4
Name: jinja-rdf
Version: 0.1.6
Summary: 
License-Expression: EUPL-1.2
License-File: LICENSE.txt
Author: Natanael Arndt
Author-email: arndtn@gmail.com
Requires-Python: >=3.11,<4.0
Classifier: Programming Language :: Python :: 3
Classifier: Programming Language :: Python :: 3.11
Classifier: Programming Language :: Python :: 3.12
Classifier: Programming Language :: Python :: 3.13
Classifier: Programming Language :: Python :: 3.14
Requires-Dist: jinja2 (>=3.1.4,<4.0.0)
Requires-Dist: rdflib (>=7.0.0,<9.0.0)
Project-URL: Repository, https://github.com/aksw/jinja-rdf
